README.md
setup.py
alphabetic_timestamp/__init__.py
alphabetic_timestamp.egg-info/PKG-INFO
alphabetic_timestamp.egg-info/SOURCES.txt
alphabetic_timestamp.egg-info/dependency_links.txt
alphabetic_timestamp.egg-info/top_level.txt