Metadata-Version: 2.1
Name: alphabetic-timestamp
Version: 1.1.5
Summary: This is small Python package which encode standard timestamp to shorted form by using alphabetic symbols.
Home-page: https://github.com/ShadowCodeCz/alphabetic_timestamp
Author: ShadowCodeCz
Author-email: shadow.code.cz@gmail.com
License: GNU Affero General Public License v3 or later (AGPLv3+)
Project-URL: Source, https://github.com/ShadowCodeCz/alphabetic_timestamp
Project-URL: Tracker, https://github.com/ShadowCodeCz/alphabetic_timestamp/issues
Keywords: timestamp alphabetic
Platform: UNKNOWN
Classifier: Development Status :: 5 - Production/Stable
Classifier: Intended Audience :: Developers
Classifier: Programming Language :: Python :: 2.7
Classifier: Programming Language :: Python :: 3.4
Classifier: Programming Language :: Python :: 3.5
Classifier: Programming Language :: Python :: 3.6
Classifier: Programming Language :: Python :: 3.7
Classifier: Programming Language :: Python :: 3.8
Classifier: Programming Language :: Python :: 3.9
Classifier: License :: OSI Approved :: GNU Affero General Public License v3 or later (AGPLv3+)
Classifier: Operating System :: OS Independent
